{
  "reference": "Provérbios 28",
  "verses": [
    {
      "book_id": "PRO",
      "book_name": "Provérbios",
      "chapter": 28,
      "verse": 1,
      "text": "Fogem os ímpios, sem que ninguém os persiga; mas os justos são ousados como o leão.   "
    },
    {
      "book_id": "PRO",
      "book_name": "Provérbios",
      "chapter": 28,
      "verse": 2,
      "text": "Por causa da transgressão duma terra são muitos os seus príncipes; mas por virtude de homens prudentes e entendidos, ela subsistirá por longo tempo.   "
    },
    {
      "book_id": "PRO",
      "book_name": "Provérbios",
      "chapter": 28,
      "verse": 3,
      "text": "O homem pobre que oprime os pobres, é como chuva impetuosa, que não deixa trigo nenhum.   "
    },
    {
      "book_id": "PRO",
      "book_name": "Provérbios",
      "chapter": 28,
      "verse": 4,
      "text": "Os que abandonam a lei louvam os ímpios; mas os que guardam a lei pelejam contra eles.   "
    },
    {
      "book_id": "PRO",
      "book_name": "Provérbios",
      "chapter": 28,
      "verse": 5,
      "text": "Os homens maus não entendem a justiça; mas os que buscam ao Senhor a entendem plenamente.   "
    },
    {
      "book_id": "PRO",
      "book_name": "Provérbios",
      "chapter": 28,
      "verse": 6,
      "text": "Melhor é o pobre que anda na sua integridade, do que o rico perverso nos seus caminhos.   "
    },
    {
      "book_id": "PRO",
      "book_name": "Provérbios",
      "chapter": 28,
      "verse": 7,
      "text": "O que guarda a lei é filho sábio; mas o companheiro dos comilões envergonha a seu pai.   "
    },
    {
      "book_id": "PRO",
      "book_name": "Provérbios",
      "chapter": 28,
      "verse": 8,
      "text": "O que aumenta a sua riqueza com juros e usura, ajunta-a para o que se compadece do pobre.   "
    },
    {
      "book_id": "PRO",
      "book_name": "Provérbios",
      "chapter": 28,
      "verse": 9,
      "text": "O que desvia os seus ouvidos de ouvir a lei, até a sua oração é abominável.   "
    },
    {
      "book_id": "PRO",
      "book_name": "Provérbios",
      "chapter": 28,
      "verse": 10,
      "text": "O que faz com que os retos se desviem para um mau caminho, ele mesmo cairá na cova que abriu; mas os inocentes herdarão o bem.   "
    },
    {
      "book_id": "PRO",
      "book_name": "Provérbios",
      "chapter": 28,
      "verse": 11,
      "text": "O homem rico é sábio aos seus próprios olhos; mas o pobre que tem entendimento o esquadrinha.   "
    },
    {
      "book_id": "PRO",
      "book_name": "Provérbios",
      "chapter": 28,
      "verse": 12,
      "text": "Quando os justos triunfam há grande, glória; mas quando os ímpios sobem, escondem-se os homens.   "
    },
    {
      "book_id": "PRO",
      "book_name": "Provérbios",
      "chapter": 28,
      "verse": 13,
      "text": "O que encobre as suas transgressões nunca prosperará; mas o que as confessa e deixa, alcançará misericórdia.   "
    },
    {
      "book_id": "PRO",
      "book_name": "Provérbios",
      "chapter": 28,
      "verse": 14,
      "text": "Feliz é o homem que teme ao Senhor continuamente; mas o que endurece o seu coração virá a cair no mal.   "
    },
    {
      "book_id": "PRO",
      "book_name": "Provérbios",
      "chapter": 28,
      "verse": 15,
      "text": "Como leão bramidor, e urso faminto, assim é o ímpio que domina sobre um povo pobre.   "
    },
    {
      "book_id": "PRO",
      "book_name": "Provérbios",
      "chapter": 28,
      "verse": 16,
      "text": "O príncipe falto de entendimento é também opressor cruel; mas o que aborrece a avareza prolongará os seus dias.   "
    },
    {
      "book_id": "PRO",
      "book_name": "Provérbios",
      "chapter": 28,
      "verse": 17,
      "text": "O homem culpado do sangue de qualquer pessoa será fugitivo até a morte; ninguém o ajude.   "
    },
    {
      "book_id": "PRO",
      "book_name": "Provérbios",
      "chapter": 28,
      "verse": 18,
      "text": "O que anda retamente salvar-se-á; mas o perverso em seus caminhos cairá de repente.   "
    },
    {
      "book_id": "PRO",
      "book_name": "Provérbios",
      "chapter": 28,
      "verse": 19,
      "text": "O que lavra a sua terra se fartará de pão; mas o que segue os ociosos se encherá de pobreza.   "
    },
    {
      "book_id": "PRO",
      "book_name": "Provérbios",
      "chapter": 28,
      "verse": 20,
      "text": "O homem fiel gozará de abundantes bênçãos; mas o que se apressa a enriquecer não ficará impune.   "
    },
    {
      "book_id": "PRO",
      "book_name": "Provérbios",
      "chapter": 28,
      "verse": 21,
      "text": "Fazer acepção de pessoas não é bom; mas até por um bocado de pão prevaricará o homem.   "
    },
    {
      "book_id": "PRO",
      "book_name": "Provérbios",
      "chapter": 28,
      "verse": 22,
      "text": "Aquele que é cobiçoso corre atrás das riquezas; e não sabe que há de vir sobre ele a penúria.   "
    },
    {
      "book_id": "PRO",
      "book_name": "Provérbios",
      "chapter": 28,
      "verse": 23,
      "text": "O que repreende a um homem achará depois mais favor do que aquele que lisonjeia com a língua.   "
    },
    {
      "book_id": "PRO",
      "book_name": "Provérbios",
      "chapter": 28,
      "verse": 24,
      "text": "O que rouba a seu pai, ou a sua mãe, e diz: Isso não é transgressão; esse é companheiro do destruidor.   "
    },
    {
      "book_id": "PRO",
      "book_name": "Provérbios",
      "chapter": 28,
      "verse": 25,
      "text": "O cobiçoso levanta contendas; mas o que confia no senhor prosperará.   "
    },
    {
      "book_id": "PRO",
      "book_name": "Provérbios",
      "chapter": 28,
      "verse": 26,
      "text": "O que confia no seu próprio coração é insensato; mas o que anda sabiamente será livre.   "
    },
    {
      "book_id": "PRO",
      "book_name": "Provérbios",
      "chapter": 28,
      "verse": 27,
      "text": "O que dá ao pobre não terá falta; mas o que esconde os seus olhos terá muitas maldições.   "
    },
    {
      "book_id": "PRO",
      "book_name": "Provérbios",
      "chapter": 28,
      "verse": 28,
      "text": "Quando os ímpios sobem, escondem-se os homens; mas quando eles perecem, multiplicam-se os justos.   "
    }
  ],
  "text": "Fogem os ímpios, sem que ninguém os persiga; mas os justos são ousados como o leão.   Por causa da transgressão duma terra são muitos os seus príncipes; mas por virtude de homens prudentes e entendidos, ela subsistirá por longo tempo.   O homem pobre que oprime os pobres, é como chuva impetuosa, que não deixa trigo nenhum.   Os que abandonam a lei louvam os ímpios; mas os que guardam a lei pelejam contra eles.   Os homens maus não entendem a justiça; mas os que buscam ao Senhor a entendem plenamente.   Melhor é o pobre que anda na sua integridade, do que o rico perverso nos seus caminhos.   O que guarda a lei é filho sábio; mas o companheiro dos comilões envergonha a seu pai.   O que aumenta a sua riqueza com juros e usura, ajunta-a para o que se compadece do pobre.   O que desvia os seus ouvidos de ouvir a lei, até a sua oração é abominável.   O que faz com que os retos se desviem para um mau caminho, ele mesmo cairá na cova que abriu; mas os inocentes herdarão o bem.   O homem rico é sábio aos seus próprios olhos; mas o pobre que tem entendimento o esquadrinha.   Quando os justos triunfam há grande, glória; mas quando os ímpios sobem, escondem-se os homens.   O que encobre as suas transgressões nunca prosperará; mas o que as confessa e deixa, alcançará misericórdia.   Feliz é o homem que teme ao Senhor continuamente; mas o que endurece o seu coração virá a cair no mal.   Como leão bramidor, e urso faminto, assim é o ímpio que domina sobre um povo pobre.   O príncipe falto de entendimento é também opressor cruel; mas o que aborrece a avareza prolongará os seus dias.   O homem culpado do sangue de qualquer pessoa será fugitivo até a morte; ninguém o ajude.   O que anda retamente salvar-se-á; mas o perverso em seus caminhos cairá de repente.   O que lavra a sua terra se fartará de pão; mas o que segue os ociosos se encherá de pobreza.   O homem fiel gozará de abundantes bênçãos; mas o que se apressa a enriquecer não ficará impune.   Fazer acepção de pessoas não é bom; mas até por um bocado de pão prevaricará o homem.   Aquele que é cobiçoso corre atrás das riquezas; e não sabe que há de vir sobre ele a penúria.   O que repreende a um homem achará depois mais favor do que aquele que lisonjeia com a língua.   O que rouba a seu pai, ou a sua mãe, e diz: Isso não é transgressão; esse é companheiro do destruidor.   O cobiçoso levanta contendas; mas o que confia no senhor prosperará.   O que confia no seu próprio coração é insensato; mas o que anda sabiamente será livre.   O que dá ao pobre não terá falta; mas o que esconde os seus olhos terá muitas maldições.   Quando os ímpios sobem, escondem-se os homens; mas quando eles perecem, multiplicam-se os justos.   ",
  "translation_id": "almeida",
  "translation_name": "João Ferreira de Almeida",
  "translation_note": "Public Domain"
}