{
  "reference": "Salmos 146",
  "verses": [
    {
      "book_id": "PSA",
      "book_name": "Salmos",
      "chapter": 146,
      "verse": 1,
      "text": "Louvai ao Senhor.Ó minha alma, louva ao Senhor.   "
    },
    {
      "book_id": "PSA",
      "book_name": "Salmos",
      "chapter": 146,
      "verse": 2,
      "text": "Louvarei ao Senhor durante a minha vida; cantarei louvores ao meu Deus enquanto viver.   "
    },
    {
      "book_id": "PSA",
      "book_name": "Salmos",
      "chapter": 146,
      "verse": 3,
      "text": "Não confieis em príncipes, nem em filho de homem, em quem não há auxílio.   "
    },
    {
      "book_id": "PSA",
      "book_name": "Salmos",
      "chapter": 146,
      "verse": 4,
      "text": "Sai-lhe o espírito, e ele volta para a terra; naquele mesmo dia perecem os seus pensamentos.   "
    },
    {
      "book_id": "PSA",
      "book_name": "Salmos",
      "chapter": 146,
      "verse": 5,
      "text": "Bem-aventurado aquele que tem o Deus de Jacó por seu auxílio, e cuja esperança está no Senhor seu Deus   "
    },
    {
      "book_id": "PSA",
      "book_name": "Salmos",
      "chapter": 146,
      "verse": 6,
      "text": "que fez os céus e a terra, o mar e tudo quanto neles há, e que guarda a verdade para sempre;   "
    },
    {
      "book_id": "PSA",
      "book_name": "Salmos",
      "chapter": 146,
      "verse": 7,
      "text": "que faz justiça aos oprimidos, que dá pão aos famintos. O Senhor solta os encarcerados;   "
    },
    {
      "book_id": "PSA",
      "book_name": "Salmos",
      "chapter": 146,
      "verse": 8,
      "text": "o Senhor abre os olhos aos cegos; o Senhor levanta os abatidos; o Senhor ama os justos.   "
    },
    {
      "book_id": "PSA",
      "book_name": "Salmos",
      "chapter": 146,
      "verse": 9,
      "text": "O Senhor preserva os peregrinos; ampara o órfão e a viúva; mas transtorna o caminho dos ímpios.   "
    },
    {
      "book_id": "PSA",
      "book_name": "Salmos",
      "chapter": 146,
      "verse": 10,
      "text": "O Senhor reinará eternamente: o teu Deus, ó Sião, reinará por todas as gerações. Louvai ao Senhor!   "
    }
  ],
  "text": "Louvai ao Senhor.Ó minha alma, louva ao Senhor.   Louvarei ao Senhor durante a minha vida; cantarei louvores ao meu Deus enquanto viver.   Não confieis em príncipes, nem em filho de homem, em quem não há auxílio.   Sai-lhe o espírito, e ele volta para a terra; naquele mesmo dia perecem os seus pensamentos.   Bem-aventurado aquele que tem o Deus de Jacó por seu auxílio, e cuja esperança está no Senhor seu Deus   que fez os céus e a terra, o mar e tudo quanto neles há, e que guarda a verdade para sempre;   que faz justiça aos oprimidos, que dá pão aos famintos. O Senhor solta os encarcerados;   o Senhor abre os olhos aos cegos; o Senhor levanta os abatidos; o Senhor ama os justos.   O Senhor preserva os peregrinos; ampara o órfão e a viúva; mas transtorna o caminho dos ímpios.   O Senhor reinará eternamente: o teu Deus, ó Sião, reinará por todas as gerações. Louvai ao Senhor!   ",
  "translation_id": "almeida",
  "translation_name": "João Ferreira de Almeida",
  "translation_note": "Public Domain"
}